LICENSE
MANIFEST.in
README.md
README_PKG.md
setup.cfg
setup.py
dicom3d/__init__.py
dicom3d/dataset.py
dicom3d/dicomdir.py
dicom3d/geometry.py
dicom3d/plotter.py
dicom3d/section.py
dicom3d/series.py
dicom3d.egg-info/PKG-INFO
dicom3d.egg-info/SOURCES.txt
dicom3d.egg-info/dependency_links.txt
dicom3d.egg-info/requires.txt
dicom3d.egg-info/top_level.txt
dicom3d/data/__init__.py
dicom3d/data/getfiles.py
dicom3d/examples/__init__.py
dicom3d/examples/__main__.py
dicom3d/examples/dicomdir/loading.py
dicom3d/examples/geometry/basic.py
dicom3d/examples/geometry/planes.py
dicom3d/examples/geometry/vectors.py
dicom3d/examples/section/basic.py
dicom3d/examples/section/make_gif.py
dicom3d/examples/section/planar.py
dicom3d/examples/section/rotation.py
dicom3d/examples/section/translation.py