Metadata-Version: 2.1
Name: dicom3d
Version: 0.9.9
Summary: Library for reconstructing arbitrary defined 3D sectionsfrom volumetric medical scans
Home-page: https://github.com/bitdefender/dicom3d
Author: Alex Mircescu
Author-email: mircescu@gmail.com
License: UNKNOWN
Keywords: python,medical,rmn,ct,dicom,reconstruction,imaging
Platform: UNKNOWN
Classifier: License :: OSI Approved :: MIT License
Classifier: Intended Audience :: Developers
Classifier: Intended Audience :: Healthcare Industry
Classifier: Intended Audience :: Science/Research
Classifier: Development Status :: 5 - Production/Stable
Classifier: Programming Language :: Python
Classifier: Programming Language :: Python :: 3.4
Classifier: Programming Language :: Python :: 3.5
Classifier: Programming Language :: Python :: 3.6
Classifier: Programming Language :: Python :: 3.7
Classifier: Operating System :: OS Independent
Classifier: Topic :: Scientific/Engineering :: Medical Science Apps.
Classifier: Topic :: Scientific/Engineering :: Physics
Classifier: Topic :: Software Development :: Libraries
Requires-Python: >=3.4
